{"errors":[],"warnings":[],"namedChunkGroups":{"polyfill":{"chunks":[0,4],"assets":["webpack-runtime-985af713c1654be788ca.js","webpack-runtime-985af713c1654be788ca.js.map","polyfill-effd73b44186fe897d74.js","polyfill-effd73b44186fe897d74.js.map"],"children":{},"childAssets":{}},"app":{"chunks":[0,3,1],"assets":["webpack-runtime-985af713c1654be788ca.js","webpack-runtime-985af713c1654be788ca.js.map","framework-66ce1c6e8de1b4304605.js","framework-66ce1c6e8de1b4304605.js.map","app-b68f133c1bf565aea4e6.js","app-b68f133c1bf565aea4e6.js.map"],"children":{},"childAssets":{}},"component---src-pages-index-js":{"chunks":[5,2],"assets":["styles.5d917c33eb53dab23b92.css","styles-29163f9dced6fe4a408a.js","styles-29163f9dced6fe4a408a.js.map","component---src-pages-index-js-f4e84ff1bd1a753488a9.js","component---src-pages-index-js-f4e84ff1bd1a753488a9.js.map"],"children":{},"childAssets":{}}},"assetsByChunkName":{"polyfill":["webpack-runtime-985af713c1654be788ca.js","polyfill-effd73b44186fe897d74.js"],"app":["webpack-runtime-985af713c1654be788ca.js","framework-66ce1c6e8de1b4304605.js","app-b68f133c1bf565aea4e6.js"],"component---src-pages-index-js":["styles.5d917c33eb53dab23b92.css","styles-29163f9dced6fe4a408a.js","component---src-pages-index-js-f4e84ff1bd1a753488a9.js"]}}